<annotation>
	<folder>our_images</folder>
	<filename>hive061.jpg</filename>
	<path>C:\Users\eemrapt\Desktop\our_images\hive061.jpg</path>
	<source>
		<database>Unknown</database>
	</source>
	<size>
		<width>590</width>
		<height>460</height>
		<depth>3</depth>
	</size>
	<segmented>0</segmented>
	<object>
		<name>no_pollen</name>
		<pose>Unspecified</pose>
		<truncated>0</truncated>
		<difficult>0</difficult>
		<bndbox>
			<xmin>182</xmin>
			<ymin>86</ymin>
			<xmax>220</xmax>
			<ymax>144</ymax>
		</bndbox>
	</object>
	<object>
		<name>no_pollen</name>
		<pose>Unspecified</pose>
		<truncated>0</truncated>
		<difficult>0</difficult>
		<bndbox>
			<xmin>351</xmin>
			<ymin>64</ymin>
			<xmax>420</xmax>
			<ymax>127</ymax>
		</bndbox>
	</object>
	<object>
		<name>no_pollen</name>
		<pose>Unspecified</pose>
		<truncated>0</truncated>
		<difficult>0</difficult>
		<bndbox>
			<xmin>395</xmin>
			<ymin>224</ymin>
			<xmax>456</xmax>
			<ymax>265</ymax>
		</bndbox>
	</object>
	<object>
		<name>no_pollen</name>
		<pose>Unspecified</pose>
		<truncated>0</truncated>
		<difficult>0</difficult>
		<bndbox>
			<xmin>357</xmin>
			<ymin>177</ymin>
			<xmax>427</xmax>
			<ymax>212</ymax>
		</bndbox>
	</object>
	<object>
		<name>no_pollen</name>
		<pose>Unspecified</pose>
		<truncated>0</truncated>
		<difficult>0</difficult>
		<bndbox>
			<xmin>341</xmin>
			<ymin>147</ymin>
			<xmax>402</xmax>
			<ymax>172</ymax>
		</bndbox>
	</object>
	<object>
		<name>no_pollen</name>
		<pose>Unspecified</pose>
		<truncated>1</truncated>
		<difficult>0</difficult>
		<bndbox>
			<xmin>548</xmin>
			<ymin>153</ymin>
			<xmax>590</xmax>
			<ymax>190</ymax>
		</bndbox>
	</object>
	<object>
		<name>no_pollen</name>
		<pose>Unspecified</pose>
		<truncated>1</truncated>
		<difficult>0</difficult>
		<bndbox>
			<xmin>560</xmin>
			<ymin>193</ymin>
			<xmax>590</xmax>
			<ymax>243</ymax>
		</bndbox>
	</object>
</annotation>
