<annotation>
	<folder>s3_imgs</folder>
	<filename>ID_0_2021-08-04_19-12-01.jpeg</filename>
	<path>C:\Users\eemrapt\Desktop\s3_imgs\ID_0_2021-08-04_19-12-01.jpeg</path>
	<source>
		<database>Unknown</database>
	</source>
	<size>
		<width>590</width>
		<height>460</height>
		<depth>3</depth>
	</size>
	<segmented>0</segmented>
	<object>
		<name>no_pollen</name>
		<pose>Unspecified</pose>
		<truncated>0</truncated>
		<difficult>0</difficult>
		<bndbox>
			<xmin>173</xmin>
			<ymin>188</ymin>
			<xmax>222</xmax>
			<ymax>240</ymax>
		</bndbox>
	</object>
	<object>
		<name>no_pollen</name>
		<pose>Unspecified</pose>
		<truncated>0</truncated>
		<difficult>0</difficult>
		<bndbox>
			<xmin>253</xmin>
			<ymin>178</ymin>
			<xmax>294</xmax>
			<ymax>219</ymax>
		</bndbox>
	</object>
	<object>
		<name>no_pollen</name>
		<pose>Unspecified</pose>
		<truncated>0</truncated>
		<difficult>0</difficult>
		<bndbox>
			<xmin>278</xmin>
			<ymin>144</ymin>
			<xmax>327</xmax>
			<ymax>174</ymax>
		</bndbox>
	</object>
	<object>
		<name>no_pollen</name>
		<pose>Unspecified</pose>
		<truncated>0</truncated>
		<difficult>0</difficult>
		<bndbox>
			<xmin>289</xmin>
			<ymin>200</ymin>
			<xmax>324</xmax>
			<ymax>251</ymax>
		</bndbox>
	</object>
	<object>
		<name>no_pollen</name>
		<pose>Unspecified</pose>
		<truncated>0</truncated>
		<difficult>0</difficult>
		<bndbox>
			<xmin>342</xmin>
			<ymin>175</ymin>
			<xmax>380</xmax>
			<ymax>219</ymax>
		</bndbox>
	</object>
	<object>
		<name>no_pollen</name>
		<pose>Unspecified</pose>
		<truncated>0</truncated>
		<difficult>0</difficult>
		<bndbox>
			<xmin>343</xmin>
			<ymin>217</ymin>
			<xmax>381</xmax>
			<ymax>270</ymax>
		</bndbox>
	</object>
	<object>
		<name>no_pollen</name>
		<pose>Unspecified</pose>
		<truncated>0</truncated>
		<difficult>0</difficult>
		<bndbox>
			<xmin>403</xmin>
			<ymin>228</ymin>
			<xmax>442</xmax>
			<ymax>279</ymax>
		</bndbox>
	</object>
	<object>
		<name>no_pollen</name>
		<pose>Unspecified</pose>
		<truncated>0</truncated>
		<difficult>0</difficult>
		<bndbox>
			<xmin>409</xmin>
			<ymin>156</ymin>
			<xmax>453</xmax>
			<ymax>204</ymax>
		</bndbox>
	</object>
	<object>
		<name>no_pollen</name>
		<pose>Unspecified</pose>
		<truncated>0</truncated>
		<difficult>0</difficult>
		<bndbox>
			<xmin>457</xmin>
			<ymin>197</ymin>
			<xmax>506</xmax>
			<ymax>249</ymax>
		</bndbox>
	</object>
	<object>
		<name>no_pollen</name>
		<pose>Unspecified</pose>
		<truncated>0</truncated>
		<difficult>0</difficult>
		<bndbox>
			<xmin>487</xmin>
			<ymin>159</ymin>
			<xmax>544</xmax>
			<ymax>197</ymax>
		</bndbox>
	</object>
	<object>
		<name>no_pollen</name>
		<pose>Unspecified</pose>
		<truncated>0</truncated>
		<difficult>0</difficult>
		<bndbox>
			<xmin>501</xmin>
			<ymin>196</ymin>
			<xmax>559</xmax>
			<ymax>230</ymax>
		</bndbox>
	</object>
	<object>
		<name>no_pollen</name>
		<pose>Unspecified</pose>
		<truncated>0</truncated>
		<difficult>0</difficult>
		<bndbox>
			<xmin>514</xmin>
			<ymin>224</ymin>
			<xmax>559</xmax>
			<ymax>280</ymax>
		</bndbox>
	</object>
	<object>
		<name>no_pollen</name>
		<pose>Unspecified</pose>
		<truncated>0</truncated>
		<difficult>0</difficult>
		<bndbox>
			<xmin>503</xmin>
			<ymin>283</ymin>
			<xmax>540</xmax>
			<ymax>341</ymax>
		</bndbox>
	</object>
	<object>
		<name>no_pollen</name>
		<pose>Unspecified</pose>
		<truncated>0</truncated>
		<difficult>0</difficult>
		<bndbox>
			<xmin>452</xmin>
			<ymin>374</ymin>
			<xmax>507</xmax>
			<ymax>407</ymax>
		</bndbox>
	</object>
	<object>
		<name>no_pollen</name>
		<pose>Unspecified</pose>
		<truncated>1</truncated>
		<difficult>0</difficult>
		<bndbox>
			<xmin>562</xmin>
			<ymin>238</ymin>
			<xmax>590</xmax>
			<ymax>275</ymax>
		</bndbox>
	</object>
	<object>
		<name>no_pollen</name>
		<pose>Unspecified</pose>
		<truncated>1</truncated>
		<difficult>0</difficult>
		<bndbox>
			<xmin>559</xmin>
			<ymin>196</ymin>
			<xmax>590</xmax>
			<ymax>222</ymax>
		</bndbox>
	</object>
	<object>
		<name>no_pollen</name>
		<pose>Unspecified</pose>
		<truncated>1</truncated>
		<difficult>0</difficult>
		<bndbox>
			<xmin>565</xmin>
			<ymin>165</ymin>
			<xmax>590</xmax>
			<ymax>194</ymax>
		</bndbox>
	</object>
</annotation>
